streamlit_monaco_code_editor/__init__.py
streamlit_monaco_code_editor/example.py
streamlit_monaco_code_editor/test.py
streamlit_monaco_code_editor/version.py
streamlit_monaco_code_editor/frontend/build/asset-manifest.json
streamlit_monaco_code_editor/frontend/build/bootstrap.min.css
streamlit_monaco_code_editor/frontend/build/index.html
streamlit_monaco_code_editor/frontend/build/static/js/main.120bf940.js
streamlit_monaco_code_editor/frontend/build/static/js/main.120bf940.js.LICENSE.txt
streamlit_monaco_code_editor/frontend/build/static/js/main.120bf940.js.map
streamlit_monaco_code_editor/frontend/build/static/js/main.73a431e4.js
streamlit_monaco_code_editor/frontend/build/static/js/main.73a431e4.js.LICENSE.txt
streamlit_monaco_code_editor/frontend/build/static/js/main.73a431e4.js.map
streamlit_monaco_code_editor/frontend/build/static/js/main.7b73c5fe.js
streamlit_monaco_code_editor/frontend/build/static/js/main.7b73c5fe.js.LICENSE.txt
streamlit_monaco_code_editor/frontend/build/static/js/main.7b73c5fe.js.map
streamlit_monaco_code_editor-0.0.4.dist-info/LICENSE.txt
streamlit_monaco_code_editor-0.0.4.dist-info/METADATA
streamlit_monaco_code_editor-0.0.4.dist-info/WHEEL
streamlit_monaco_code_editor-0.0.4.dist-info/top_level.txt
streamlit_monaco_code_editor-0.0.4.dist-info/RECORD
