Metadata-Version: 2.1
Name: streamlit_monaco_code_editor
Version: 0.0.4
Summary: A wrapper of the Monaco Editor for Streamlit
Home-page: https://github.com/li-xin-yi/streamlit_monaco_code_editor
Author: Xinyi Li
Author-email: wolixinyi@gmail.com
Requires-Python: >=3.7
License-File: LICENSE.txt
Requires-Dist: streamlit >=0.63
Provides-Extra: devel
Requires-Dist: wheel ; extra == 'devel'
Requires-Dist: pytest ==7.4.0 ; extra == 'devel'
Requires-Dist: playwright ==1.39.0 ; extra == 'devel'
Requires-Dist: requests ==2.31.0 ; extra == 'devel'
Requires-Dist: pytest-playwright-snapshot ==1.0 ; extra == 'devel'
Requires-Dist: pytest-rerunfailures ==12.0 ; extra == 'devel'
